{"total":43,"pageSize":10,"pageCount":5,"data":[{"title":"我的2017年网络收藏夹整理汇总","slug":"我的2017年网络收藏夹整理汇总","date":"2018-02-03T11:55:38.000Z","updated":"2019-03-18T06:32:49.000Z","comments":true,"path":"api/articles/我的2017年网络收藏夹整理汇总.json","excerpt":null,"keywords":null,"cover":null,"content":null,"raw":null,"categories":[{"name":"网络·计算机","path":"api/categories/网络·计算机.json"}],"tags":[{"name":"互联网","path":"api/tags/互联网.json"},{"name":"学习","path":"api/tags/学习.json"},{"name":"收藏","path":"api/tags/收藏.json"},{"name":"综合","path":"api/tags/综合.json"}]},{"title":"【转载】比特大陆把台积电12nm产能全抢了","slug":"【转载】比特大陆把台积电12nm产能全抢了","date":"2018-02-01T07:54:22.000Z","updated":"2019-11-07T05:49:18.000Z","comments":true,"path":"api/articles/【转载】比特大陆把台积电12nm产能全抢了.json","excerpt":null,"keywords":null,"cover":null,"content":null,"raw":null,"categories":[{"name":"物联网·电子开发","path":"api/categories/物联网·电子开发.json"}],"tags":[{"name":"区块链","path":"api/tags/区块链.json"},{"name":"台积电","path":"api/tags/台积电.json"},{"name":"比特大陆","path":"api/tags/比特大陆.json"},{"name":"IC","path":"api/tags/IC.json"}]},{"title":"MMDVM热点板DMR模式简版配置过程","slug":"MMDVM热点板简版配置过程","date":"2017-11-04T14:28:05.000Z","updated":"2020-09-30T09:00:45.803Z","comments":true,"path":"api/articles/MMDVM热点板简版配置过程.json","excerpt":null,"keywords":null,"cover":"http://imgs.bd7iwd.online//15098070757937.jpg","content":null,"raw":null,"categories":[{"name":"HAM·业余无线电","path":"api/categories/HAM·业余无线电.json"}],"tags":[{"name":"HAM","path":"api/tags/HAM.json"},{"name":"无线电","path":"api/tags/无线电.json"},{"name":"DMR","path":"api/tags/DMR.json"},{"name":"树莓派","path":"api/tags/树莓派.json"},{"name":"MMDVM","path":"api/tags/MMDVM.json"},{"name":"BD7IWD","path":"api/tags/BD7IWD.json"}]},{"title":"致青春","slug":"致青春","date":"2017-07-04T10:58:21.000Z","updated":"2019-03-18T06:32:37.000Z","comments":true,"path":"api/articles/致青春.json","excerpt":null,"keywords":null,"cover":null,"content":null,"raw":null,"categories":[{"name":"文学·读书","path":"api/categories/文学·读书.json"}],"tags":[{"name":"青春","path":"api/tags/青春.json"},{"name":"回忆","path":"api/tags/回忆.json"}]},{"title":"小米对讲机测评","slug":"小米对讲机测评","date":"2017-03-03T11:03:05.000Z","updated":"2019-11-07T05:01:55.000Z","comments":true,"path":"api/articles/小米对讲机测评.json","excerpt":null,"keywords":null,"cover":"http://imgs.bd7iwd.online//%E7%BA%AF%E5%A4%96%E5%8C%85%E8%A3%85.JPG","content":null,"raw":null,"categories":[{"name":"HAM·业余无线电","path":"api/categories/HAM·业余无线电.json"}],"tags":[{"name":"HAM","path":"api/tags/HAM.json"},{"name":"BD7IWD","path":"api/tags/BD7IWD.json"},{"name":"小米","path":"api/tags/小米.json"},{"name":"对讲机","path":"api/tags/对讲机.json"},{"name":"测评","path":"api/tags/测评.json"},{"name":"开箱","path":"api/tags/开箱.json"}]},{"title":"区块链在物联网上面的应用构想","slug":"区块链在物联网上面的应用构想","date":"2016-12-26T17:33:44.000Z","updated":"2019-03-18T06:32:48.000Z","comments":true,"path":"api/articles/区块链在物联网上面的应用构想.json","excerpt":null,"keywords":null,"cover":null,"content":null,"raw":null,"categories":[{"name":"物联网·电子开发","path":"api/categories/物联网·电子开发.json"}],"tags":[{"name":"区块链","path":"api/tags/区块链.json"},{"name":"物联网","path":"api/tags/物联网.json"},{"name":"信息安全","path":"api/tags/信息安全.json"},{"name":"去中心化","path":"api/tags/去中心化.json"}]},{"title":"新中国建国后几个逗逼皇帝","slug":"新中国建国后几个逗逼皇帝","date":"2016-12-05T09:24:09.000Z","updated":"2019-03-18T06:32:40.000Z","comments":true,"path":"api/articles/新中国建国后几个逗逼皇帝.json","excerpt":null,"keywords":null,"cover":null,"content":null,"raw":null,"categories":[{"name":"文学·读书","path":"api/categories/文学·读书.json"}],"tags":[{"name":"历史","path":"api/tags/历史.json"},{"name":"新中国","path":"api/tags/新中国.json"},{"name":"逗逼","path":"api/tags/逗逼.json"},{"name":"皇帝","path":"api/tags/皇帝.json"}]},{"title":"日韩为什么怕朝鲜打卫星","slug":"日韩为什么怕朝鲜打卫星","date":"2016-09-30T02:14:13.000Z","updated":"2020-09-30T06:41:59.704Z","comments":true,"path":"api/articles/日韩为什么怕朝鲜打卫星.json","excerpt":null,"keywords":null,"cover":"http://imgs.bd7iwd.online//cx001.jpg","content":null,"raw":null,"categories":[{"name":"脑洞奇文","path":"api/categories/脑洞奇文.json"}],"tags":[{"name":"BD7IWD","path":"api/tags/BD7IWD.json"},{"name":"脑洞","path":"api/tags/脑洞.json"},{"name":"朝鲜","path":"api/tags/朝鲜.json"},{"name":"卫星","path":"api/tags/卫星.json"},{"name":"脑洞大开","path":"api/tags/脑洞大开.json"},{"name":"金三胖","path":"api/tags/金三胖.json"}]},{"title":"何为少年","slug":"何为少年","date":"2016-09-19T11:54:12.000Z","updated":"2019-03-18T06:32:42.000Z","comments":true,"path":"api/articles/何为少年.json","excerpt":null,"keywords":null,"cover":null,"content":null,"raw":null,"categories":[{"name":"文学·读书","path":"api/categories/文学·读书.json"}],"tags":[{"name":"年轻","path":"api/tags/年轻.json"},{"name":"少年侠气","path":"api/tags/少年侠气.json"}]},{"title":"如何更好地阅读马尔克斯的《百年孤独》 - BD7IWD","slug":"如何更好地阅读马尔克斯的《百年孤独》","date":"2016-09-07T10:00:27.000Z","updated":"2019-03-18T06:32:39.000Z","comments":true,"path":"api/articles/如何更好地阅读马尔克斯的《百年孤独》.json","excerpt":null,"keywords":null,"cover":null,"content":null,"raw":null,"categories":[{"name":"文学·读书","path":"api/categories/文学·读书.json"}],"tags":[{"name":"百年孤独","path":"api/tags/百年孤独.json"},{"name":"加西亚·马尔克斯","path":"api/tags/加西亚·马尔克斯.json"},{"name":"阅读","path":"api/tags/阅读.json"}]}]}