{"name":"对讲机","postlist":[{"title":"小米对讲机测评","slug":"小米对讲机测评","date":"2017-03-03T11:03:05.000Z","updated":"2019-11-07T05:01:55.000Z","comments":true,"path":"api/articles/小米对讲机测评.json","excerpt":null,"keywords":null,"cover":"http://imgs.bd7iwd.online//%E7%BA%AF%E5%A4%96%E5%8C%85%E8%A3%85.JPG","content":null,"raw":null,"categories":[{"name":"HAM·业余无线电","path":"api/categories/HAM·业余无线电.json"}],"tags":[{"name":"HAM","path":"api/tags/HAM.json"},{"name":"BD7IWD","path":"api/tags/BD7IWD.json"},{"name":"小米","path":"api/tags/小米.json"},{"name":"对讲机","path":"api/tags/对讲机.json"},{"name":"测评","path":"api/tags/测评.json"},{"name":"开箱","path":"api/tags/开箱.json"}]}]}